README.md
setuplog/__init__.py
setuplog/adaptors.py
setuplog/decorator.py
setuplog/formatters.py
setuplog/logger.py
setuplog/py.typed
setuplog/setup.py
setuplog-0.4.1.dist-info/LICENSE
setuplog-0.4.1.dist-info/WHEEL
setuplog-0.4.1.dist-info/METADATA
setuplog-0.4.1.dist-info/RECORD
