Metadata-Version: 2.1
Name: setuplog
Version: 0.4.1
Summary: 
Home-page: https://github.com/schireson/setuplog
License: MIT
Keywords: logging,logger,log
Requires-Python: >=3.6.0,<4
Classifier: License :: OSI Approved :: MIT License
Classifier: Programming Language :: Python :: 3
Classifier: Programming Language :: Python :: 3.6
Classifier: Programming Language :: Python :: 3.7
Classifier: Programming Language :: Python :: 3.8
Classifier: Programming Language :: Python :: 3.9
Classifier: Programming Language :: Python :: 3.10
Classifier: Programming Language :: Python :: 3.11
Project-URL: Repository, https://github.com/schireson/setuplog
